Metadata-Version: 2.1
Name: django-toosimple-q
Version: 1.0.0.post1
Summary: A simplistic task queue and cron-like scheduler for Django
Home-page: https://github.com/olivierdalang/django-toosimple-q
Author: Olivier Dalang
Author-email: olivier.dalang@gmail.com
License: MIT
Keywords: django-toosimple-q
Classifier: Development Status :: 3 - Alpha
Classifier: Framework :: Django :: 2.2
Classifier: Intended Audience :: Developers
Classifier: License :: OSI Approved :: BSD License
Classifier: Natural Language :: English
Classifier: Programming Language :: Python :: 3
Classifier: Programming Language :: Python :: 3.7
License-File: LICENSE
Requires-Dist: croniter >=1.3
Requires-Dist: django-picklefield >=3.0
Requires-Dist: django >=3.2
